{
  "windows": 4,
  "objective": "MAR",
  "window_mode": "unanchored",
  "train_months": 48,
  "test_months": 12,
  "step_months": 12,
  "parallel": {
    "enabled": true,
    "scope": "window_grid",
    "workers": 3
  },
  "selection_filter": {
    "exclusive_min_trades_per_year": 50
  },
  "early_exit_min_train_profit_factor": 1.0,
  "early_exit_require_train_profitable": false,
  "early_exit": true,
  "passing_windows": 0,
  "profitable_windows": 1,
  "profitable_window_rate": 0.25,
  "meets_profitable_window_benchmark": false,
  "median_test_net_profit": -587.5,
  "median_test_mar": -0.2674866066202307,
  "median_test_cagr": -0.004062140494182742,
  "median_test_max_drawdown_pct": 0.012161394856624323,
  "train_grid_reports_retained": true,
  "train_grid_report_files": [
    "backtest-campaigns/nq_treasury_auction_pressure/note_only_post_auction_short_1305/NQ/run1/walk_forward_analysis/window_001_train_grid.csv",
    "backtest-campaigns/nq_treasury_auction_pressure/note_only_post_auction_short_1305/NQ/run1/walk_forward_analysis/window_002_train_grid.csv",
    "backtest-campaigns/nq_treasury_auction_pressure/note_only_post_auction_short_1305/NQ/run1/walk_forward_analysis/window_003_train_grid.csv"
  ],
  "reuse_existing_train_grids_requested": false,
  "reused_existing_train_grids": false,
  "reused_train_grid_count": 0,
  "strict_train_grid_reuse": true,
  "phase_timings_seconds": {
    "slice_windows": 0.671348,
    "train_grid_compute": 144.864661,
    "train_grid_write": 0.010181,
    "oos_backtest": 5.9966,
    "annotate_oos_trades": 0.011811,
    "stitch_oos_trades": 0.00327
  },
  "window_timings_seconds": [
    {
      "window_id": 1.0,
      "slice_seconds": 0.084732,
      "train_grid_seconds": 38.517634,
      "train_grid_write_seconds": 0.003581,
      "oos_backtest_seconds": 1.889327,
      "total_seconds": 40.49801,
      "reused_train_grid": false
    },
    {
      "window_id": 2.0,
      "slice_seconds": 0.237133,
      "train_grid_seconds": 35.845855,
      "train_grid_write_seconds": 0.003059,
      "oos_backtest_seconds": 2.0668,
      "total_seconds": 38.165375,
      "reused_train_grid": false
    },
    {
      "window_id": 3.0,
      "slice_seconds": 0.205938,
      "train_grid_seconds": 35.606838,
      "train_grid_write_seconds": 0.003541,
      "oos_backtest_seconds": 2.040473,
      "total_seconds": 37.859759,
      "reused_train_grid": false
    },
    {
      "window_id": 4.0,
      "slice_seconds": 0.143545,
      "train_grid_seconds": 34.894333,
      "total_seconds": 35.039406,
      "early_exit": true
    }
  ],
  "stitched_oos_trades": 203,
  "stitched_oos_metrics": {
    "total_trades": 203,
    "trades_per_year": 68.58247313416537,
    "net_profit": -1490.0,
    "profit_factor": 0.9392951721328173,
    "expectancy_r": -0.022911895047528656,
    "max_drawdown": 3395.0,
    "max_drawdown_pct": 0.02255064762537363,
    "cagr": -0.0033670217611764253,
    "mar": -0.14930931550666002,
    "worst_day": -495.0,
    "best_day": 950.0,
    "best_day_concentration": 0.0,
    "max_consecutive_losses": 7,
    "positive_month_rate": 0.4166666666666667,
    "win_rate": 0.43842364532019706,
    "average_trade": -7.3399014778325125,
    "apex_rule_violations": 0,
    "apex_forced_flatten_trades": 0
  },
  "oos_evaluation_years": 4.0,
  "required_oos_mar": 1.2325578259122962,
  "incubation_selected_params": {
    "sl.params.stop_pct": 0.004,
    "tp.params.target_r_multiple": 2.0
  },
  "configured_data_subset": {},
  "resolved_data_subset": {
    "start_date": "2011-01-03",
    "end_date": "2024-11-25",
    "session_labels": [
      "RTH"
    ]
  },
  "data_subset": {
    "start_date": "2011-01-03",
    "end_date": "2024-11-25",
    "session_labels": [
      "RTH"
    ]
  },
  "actual_data_period": {
    "first_timestamp": "2011-01-03 09:30:00-05:00",
    "last_timestamp": "2024-11-25 15:59:00-05:00",
    "rows": 1338480,
    "strategy_rows": 1338480,
    "timeframe": "1m",
    "source_timeframe": "1m"
  },
  "equity_curve_csv": "backtest-campaigns/nq_treasury_auction_pressure/note_only_post_auction_short_1305/NQ/run1/walk_forward_analysis/equity_curve.csv",
  "equity_curve_html": "backtest-campaigns/nq_treasury_auction_pressure/note_only_post_auction_short_1305/NQ/run1/walk_forward_analysis/equity_curve.html",
  "equity_curve_points": 204
}