{
  "draft": {
    "campaign_id": "liquidity_sweep_example_17_july",
    "created_at": "2026-07-17",
    "duplicate_review": {
      "conclusion": "distinct",
      "ledger_queries": [
        "Liquidity sweep example 17 July",
        "liquidity_sweep"
      ],
      "reviewed_campaign_ids": [
        "es_example_liquidity_reversal"
      ],
      "substantive_distinction": "asdfasdfasdfasdlkajsd;lfjas;ldkjf;laskdj;flkjasd;lf\nasdlfkja;sldkjf;laskjdf;laksjdf\na what is going on"
    },
    "economic_edge_fingerprint": {
      "causal_mechanism": "-",
      "holding_period": "Intraday",
      "market_behavior": "???",
      "market_context": "RTH futures",
      "signal_inputs": [
        "???"
      ]
    },
    "edge_family": "liquidity_sweep",
    "expected_mechanism": "-",
    "frozen": false,
    "holding_horizon": "Intraday",
    "hypothesis": "-",
    "instrument": "ES",
    "known_failure_modes": [
      "-"
    ],
    "schema": "alphaquest.campaign-draft/v1",
    "sources": [
      {
        "authors": [
          "asdf"
        ],
        "doi": "asdf",
        "link": "http://www.google.com",
        "relevance": "asdf",
        "title": "asdf",
        "year": 2026
      }
    ],
    "timeframe": "1m",
    "title": "Liquidity sweep example 17 July"
  },
  "schema": "alphaquest.studio-autosave/v1",
  "updated_at": "2026-07-17T12:33:50.217311+00:00",
  "wizard_step": 3
}
